Metadata-Version: 1.1
Name: resattention
Version: 0.0.4
Summary: A library for implementing Gated Residual Attention CNN for image classification problems.
Home-page: https://github.com/garain/resattention
Author: Avishek Garain
Author-email: avishekgarain@gmail.com
License: MIT
Keywords: attention CNN image-classification
Platform: UNKNOWN
Classifier: Development Status :: 4 - Beta
Classifier: Intended Audience :: Developers
Classifier: Topic :: Internet
Classifier: License :: OSI Approved :: MIT License
Classifier: Programming Language :: Python
Classifier: Programming Language :: Python :: 2
Classifier: Programming Language :: Python :: 2.6
Classifier: Programming Language :: Python :: 2.7
Classifier: Programming Language :: Python :: 3
Classifier: Programming Language :: Python :: 3.3
Classifier: Programming Language :: Python :: 3.4
Classifier: Programming Language :: Python :: 3.5
